nwebclient/__init__.py
nwebclient/__main__.py
nwebclient/base.py
nwebclient/crypt.py
nwebclient/dev.py
nwebclient/image_classification.py
nwebclient/llm.py
nwebclient/machine.py
nwebclient/nc.py
nwebclient/nlp.py
nwebclient/nts.py
nwebclient/nweb.py
nwebclient/nx.py
nwebclient/openapi.py
nwebclient/runner.py
nwebclient/sd.py
nwebclient/sdb.py
nwebclient/ticker.py
nwebclient/util.py
nwebclient/visual.py
nwebclient/web.py
nwebclient/ws.py
tests/__init__.py
tests/base.py
tests/runner.py
tests/util.py
tests/visual.py
nwebclient-1.0.313.dist-info/LICENSE
nwebclient-1.0.313.dist-info/METADATA
nwebclient-1.0.313.dist-info/WHEEL
nwebclient-1.0.313.dist-info/entry_points.txt
nwebclient-1.0.313.dist-info/top_level.txt
nwebclient-1.0.313.dist-info/RECORD
