Metadata-Version: 2.1
Name: nwebclient
Version: 1.0.313
Summary: NWebClient via HTTP
Home-page: https://bsnx.net/4.0/group/pynwebclient
Author: Bjoern Salgert
Author-email: bjoern.salgert@hs-duesseldorf.de
Classifier: Programming Language :: Python :: 3
Classifier: License :: OSI Approved :: MIT License
Classifier: Operating System :: OS Independent
License-File: LICENSE
Requires-Dist: pandas
Requires-Dist: pillow (>=8.4.0)
Requires-Dist: requests (>=2.0.0)
Requires-Dist: seaborn
Requires-Dist: usersettings (>=1.0.7)
